RelayMuseum/__init__.py
RelayMuseum/urls.py
RelayMuseum/views.py
RelayMuseum/wsgi.py
RelayMuseum/settings/__init__.py
RelayMuseum/settings/base.py
RelayMuseum/settings/production.py
RelayMuseum/static/css/rm-1.css
RelayMuseum/static/img/extlink.gif
RelayMuseum/static/img/favicon.ico
RelayMuseum/static/img/valid-xhtml10.png
RelayMuseum/static/img/vcss.gif
RelayMuseum/static/img/viking_horses.png
RelayMuseum/templates/base.html
RelayMuseum/templates/index.html
RelayMuseum/templates/flatpages/default.html
RelayMuseum-0.3.0.dist-info/DESCRIPTION.rst
RelayMuseum-0.3.0.dist-info/METADATA
RelayMuseum-0.3.0.dist-info/RECORD
RelayMuseum-0.3.0.dist-info/WHEEL
RelayMuseum-0.3.0.dist-info/metadata.json
RelayMuseum-0.3.0.dist-info/top_level.txt
relay/__init__.py
relay/admin.py
relay/apps.py
relay/models.py
relay/urls.py
relay/views.py
relay/templates/relay/language_detail.html
relay/templates/relay/language_list.html
relay/templates/relay/participant_detail.html
relay/templates/relay/participant_list.html
relay/templates/relay/relay_detail.html
relay/templates/relay/relay_list.html
relay/templates/relay/ring_smooth_translation.html
relay/templates/relay/statistics.html
relay/templates/relay/torch_detail.html
relay/templates/relay/torch_list.html
relay/templatetags/__init__.py
relay/templatetags/relay_tags.py
