Metadata-Version: 2.0
Name: RelayMuseum
Version: 0.3.0
Summary: A web-museum for conlang-relays.
Home-page: https://github.com/kaleissin/RelayMuseum
Author: kaleissin
Author-email: kaleissin@gmail.com
License: UNKNOWN
Platform: any
Classifier: Development Status :: 4 - Beta
Classifier: Environment :: Web Environment
Classifier: Framework :: Django
Classifier: Intended Audience :: Developers
Classifier: License :: OSI Approved :: MIT License
Classifier: Operating System :: OS Independent
Classifier: Programming Language :: Python
Classifier: Programming Language :: Python :: 3
Classifier: Programming Language :: Python :: 3.4
Classifier: Programming Language :: Python :: 3.5
Classifier: Topic :: Software Development :: Libraries :: Application Frameworks
Classifier: Topic :: Software Development :: Libraries :: Python Modules
